{
    "key": "group_5b5ef0bdd2360",
    "title": "Component: Exhibitor of the week",
    "fields": [
        {
            "key": "field_5b5ef0c76828c",
            "label": "Exhibitor logo",
            "name": "exhibitor_logo",
            "type": "image",
            "instructions": "",
            "required": 0,
            "conditional_logic": 0,
            "wrapper": {
                "width": "",
                "class": "",
                "id": ""
            },
            "return_format": "array",
            "preview_size": "thumbnail",
            "library": "all",
            "min_width": "",
            "min_height": "",
            "min_size": "",
            "max_width": "",
            "max_height": "",
            "max_size": "",
            "mime_types": ""
        },
        {
            "key": "field_5f105d7de9fa8",
            "label": "Exhibitor logo - make circle image",
            "name": "exhibitor_logo_circle",
            "type": "true_false",
            "instructions": "",
            "required": 0,
            "conditional_logic": 0,
            "wrapper": {
                "width": "",
                "class": "",
                "id": ""
            },
            "message": "",
            "default_value": 0,
            "ui": 1,
            "ui_on_text": "",
            "ui_off_text": ""
        },
        {
            "key": "field_5b5ef0f26828d",
            "label": "Exhibitor image",
            "name": "exhibitor_image",
            "type": "image",
            "instructions": "",
            "required": 0,
            "conditional_logic": 0,
            "wrapper": {
                "width": "",
                "class": "",
                "id": ""
            },
            "return_format": "array",
            "preview_size": "thumbnail",
            "library": "all",
            "min_width": "",
            "min_height": "",
            "min_size": "",
            "max_width": "",
            "max_height": "",
            "max_size": "",
            "mime_types": ""
        },
        {
            "key": "field_5b5ef12a6828f",
            "label": "Exhibitor title",
            "name": "exhibitor_title",
            "type": "text",
            "instructions": "",
            "required": 0,
            "conditional_logic": 0,
            "wrapper": {
                "width": "",
                "class": "",
                "id": ""
            },
            "default_value": "Exhibitor of the week",
            "placeholder": "",
            "prepend": "",
            "append": "",
            "maxlength": ""
        },
        {
            "key": "field_5b5ef13868290",
            "label": "Exhibitor text",
            "name": "exhibitor_text",
            "type": "textarea",
            "instructions": "",
            "required": 0,
            "conditional_logic": 0,
            "wrapper": {
                "width": "",
                "class": "",
                "id": ""
            },
            "default_value": "",
            "placeholder": "",
            "maxlength": "",
            "rows": "",
            "new_lines": ""
        },
        {
            "key": "field_5b5ef1a668291",
            "label": "Exhibitor CTA button",
            "name": "exhibitor_cta_button",
            "type": "clone",
            "instructions": "",
            "required": 0,
            "conditional_logic": 0,
            "wrapper": {
                "width": "",
                "class": "",
                "id": ""
            },
            "clone": [
                "group_5b5ee13293c94"
            ],
            "display": "seamless",
            "layout": "block",
            "prefix_label": 0,
            "prefix_name": 1
        }
    ],
    "location": [
        [
            {
                "param": "widget",
                "operator": "!=",
                "value": "all"
            }
        ]
    ],
    "menu_order": 0,
    "position": "normal",
    "style": "default",
    "label_placement": "top",
    "instruction_placement": "label",
    "hide_on_screen": "",
    "active": 1,
    "description": "",
    "modified": 1594908270
}